duration2/__about__.py
duration2/__init__.py
duration2/base.py
duration2/datatype.py
duration2/py.typed
duration2/tasks.py
duration2-0.7.1.dist-info/METADATA
duration2-0.7.1.dist-info/WHEEL
duration2-0.7.1.dist-info/licenses/LICENSE
duration2-0.7.1.dist-info/RECORD
